pih_tls/__init__.py
pih_tls-1.3.dist-info/METADATA
pih_tls-1.3.dist-info/WHEEL
pih_tls-1.3.dist-info/top_level.txt
pih_tls-1.3.dist-info/RECORD
