Metadata-Version: 2.1
Name: pih-tls
Version: 1.3
Summary: Shared tools for PIH module
Home-page: https://pacifichosp.com/
Author: Nikita Karachentsev
Author-email: it@pacifichosp.com
License: MIT
Requires-Dist: pillow
Requires-Dist: numpy
Requires-Dist: pdf2image
